MANIFEST.in
README.md
setup.py
lib/urllib_kerberos/__init__.py
lib/urllib_kerberos/__main__.py
lib/urllib_kerberos/version.py
lib/urllib_kerberos.egg-info/PKG-INFO
lib/urllib_kerberos.egg-info/SOURCES.txt
lib/urllib_kerberos.egg-info/dependency_links.txt
lib/urllib_kerberos.egg-info/top_level.txt