Metadata-Version: 1.1
Name: urllib-kerberos
Version: 0.2.0
Summary: Kerberos over HTTP Negotiate/SPNEGO support for urllib2
Home-page: http://github.com/willthames/urllib_kerberos/
Author: Will Thames
Author-email: will@thames.id.au
License: Apache 2.0
Keywords: urllib2 kerberos http negotiate spnego
Platform: UNKNOWN
Classifier: Development Status :: 3 - Alpha
Classifier: Intended Audience :: Developers
Classifier: License :: OSI Approved :: Apache Software License
Classifier: Natural Language :: English
Classifier: Operating System :: POSIX :: Linux
Classifier: Programming Language :: Python
Classifier: Topic :: Internet :: WWW/HTTP
Classifier: Topic :: Software Development :: Libraries
Classifier: Topic :: Software Development :: Libraries :: Python Modules
Classifier: Topic :: System :: Systems Administration :: Authentication/Directory
